topicgpt/__init__.py
topicgpt/_config.py
topicgpt/base.py
topicgpt/pipeline.py
topicgpt/utils.py
topicgpt/clustering/__init__.py
topicgpt/clustering/_base_cluster.py
topicgpt/clustering/_hdbscan.py
topicgpt/clustering/_kmeans.py
topicgpt/clustering/_sampling.py
topicgpt/generation/__init__.py
topicgpt/generation/_keywords.py
topicgpt/generation/_topic.py
topicgpt/persistence/__init__.py
topicgpt/persistence/_plot.py
topicgpt/persistence/_save.py
topicgpt/preprocessing/__init__.py
topicgpt/preprocessing/_data.py
topicgpt/walmart_llm/__init__.py
topicgpt/walmart_llm/_chat_model.py
topicgpt/walmart_llm/_embed_model.py
topicgpt/walmart_llm/_llm_client.py
wm_topicgpt-0.1.5.dist-info/METADATA
wm_topicgpt-0.1.5.dist-info/WHEEL
wm_topicgpt-0.1.5.dist-info/top_level.txt
wm_topicgpt-0.1.5.dist-info/RECORD
