Metadata-Version: 2.1
Name: wm-topicgpt
Version: 0.1.5
Summary: This is a package to generate topics for the text corpus.
Requires-Python: >=3.9
Requires-Dist: numpy ==1.26.4
Requires-Dist: pandas ==2.2.1
Requires-Dist: tqdm ==4.66.2
Requires-Dist: azure-ai-textanalytics ==5.3.0
Requires-Dist: aiohttp ==3.9.3
Requires-Dist: langchain ==0.1.14
Requires-Dist: langchain-community ==0.0.31
Requires-Dist: pycryptodome ==3.10.1
Requires-Dist: tiktoken ==0.6.0
Requires-Dist: openai ==1.16.0
Requires-Dist: scikit-learn ==1.4.0
Requires-Dist: umap-learn ==0.5.5
Requires-Dist: sentence-transformers ==2.6.1
Requires-Dist: pydantic ==2.7.1
Requires-Dist: google-cloud-bigquery ==3.21.0
Requires-Dist: gradio ==4.28.3
Requires-Dist: appscript ==1.2.5
Requires-Dist: keybert ==0.8.4
Requires-Dist: pyarrow ==16.0.0
